{
  "status": {
    "code": "00",
    "message": "success",
    "totalCount": 1
  },
  "contents": {
    "subwayLine": "2호선",
    "stationName": "충정로역",
    "stationCode": "243",
    "stat": [
      {
        "startStationCode": "202",
        "startStationName": "을지로입구역",
        "endStationCode": "211",
        "endStationName": "성수역",
        "prevStationCode": "201",
        "prevStationName": "시청역",
        "updnLine": 0,
        "directAt": 0,
        "data": [
          {
            "dow": "MON",
            "hh": "08",
            "mm": "00",
            "congestionCar": [
              27,
              38,
              41,
              47,
              45,
              40,
              32,
              41,
              34,
              25
            ]
          },
          {
            "dow": "MON",
            "hh": "08",
            "mm": "10",
            "congestionCar": [
              31,
              43,
              44,
              49,
              46,
              46,
              43,
              52,
              36,
              32
            ]
          },
          {
            "dow": "MON",
            "hh": "08",
            "mm": "20",
            "congestionCar": [
              31,
              37,
              47,
              47,
              50,
              47,
              44,
              49,
              52,
              35
            ]
          },
          {
            "dow": "MON",
            "hh": "08",
            "mm": "30",
            "congestionCar": [
              29,
              29,
              38,
              40,
              48,
              44,
              35,
              51,
              38,
              29
            ]
          },
          {
            "dow": "MON",
            "hh": "08",
            "mm": "40",
            "congestionCar": [
              27,
              29,
              45,
              47,
              42,
              44,
              41,
              44,
              34,
              27
            ]
          },
          {
            "dow": "MON",
            "hh": "08",
            "mm": "50",
            "congestionCar": [
              25,
              31,
              35,
              36,
              30,
              37,
              35,
              36,
              34,
              20
            ]
          }
        ]
      },
      {
        "startStationCode": "202",
        "startStationName": "을지로입구역",
        "endStationCode": "211-R",
        "endStationName": "성수역",
        "prevStationCode": "201",
        "prevStationName": "시청역",
        "updnLine": 0,
        "directAt": 0,
        "data": [
          {
            "dow": "MON",
            "hh": "08",
            "mm": "00",
            "congestionCar": [
              27,
              38,
              41,
              47,
              45,
              40,
              32,
              41,
              34,
              25
            ]
          },
          {
            "dow": "MON",
            "hh": "08",
            "mm": "10",
            "congestionCar": [
              31,
              43,
              44,
              49,
              46,
              46,
              43,
              52,
              36,
              32
            ]
          },
          {
            "dow": "MON",
            "hh": "08",
            "mm": "20",
            "congestionCar": [
              31,
              37,
              47,
              47,
              50,
              47,
              44,
              49,
              52,
              35
            ]
          },
          {
            "dow": "MON",
            "hh": "08",
            "mm": "30",
            "congestionCar": [
              29,
              29,
              38,
              40,
              48,
              44,
              35,
              51,
              38,
              29
            ]
          },
          {
            "dow": "MON",
            "hh": "08",
            "mm": "40",
            "congestionCar": [
              27,
              29,
              45,
              47,
              42,
              44,
              41,
              44,
              34,
              27
            ]
          },
          {
            "dow": "MON",
            "hh": "08",
            "mm": "50",
            "congestionCar": [
              25,
              31,
              35,
              36,
              30,
              37,
              35,
              36,
              34,
              20
            ]
          }
        ]
      },
      {
        "startStationCode": "211",
        "startStationName": "성수역",
        "endStationCode": "202",
        "endStationName": "을지로입구역",
        "prevStationCode": "242",
        "prevStationName": "아현역",
        "updnLine": 1,
        "directAt": 0,
        "data": [
          {
            "dow": "MON",
            "hh": "08",
            "mm": "00",
            "congestionCar": [
              128,
              107,
              103,
              119,
              108,
              97,
              100,
              91,
              79,
              88
            ]
          },
          {
            "dow": "MON",
            "hh": "08",
            "mm": "10",
            "congestionCar": [
              166,
              141,
              147,
              167,
              158,
              140,
              135,
              137,
              122,
              117
            ]
          },
          {
            "dow": "MON",
            "hh": "08",
            "mm": "20",
            "congestionCar": [
              159,
              140,
              153,
              168,
              148,
              146,
              133,
              152,
              128,
              144
            ]
          },
          {
            "dow": "MON",
            "hh": "08",
            "mm": "30",
            "congestionCar": [
              174,
              159,
              162,
              194,
              175,
              177,
              181,
              173,
              149,
              136
            ]
          },
          {
            "dow": "MON",
            "hh": "08",
            "mm": "40",
            "congestionCar": [
              185,
              150,
              131,
              146,
              127,
              135,
              139,
              125,
              106,
              107
            ]
          },
          {
            "dow": "MON",
            "hh": "08",
            "mm": "50",
            "congestionCar": [
              117,
              83,
              69,
              73,
              77,
              72,
              64,
              66,
              70,
              59
            ]
          }
        ]
      },
      {
        "startStationCode": "211",
        "startStationName": "성수역",
        "endStationCode": "211",
        "endStationName": "성수역",
        "prevStationCode": "201",
        "prevStationName": "시청역",
        "updnLine": 0,
        "directAt": 0,
        "data": [
          {
            "dow": "MON",
            "hh": "08",
            "mm": "00",
            "congestionCar": [
              27,
              38,
              41,
              47,
              45,
              40,
              32,
              41,
              34,
              25
            ]
          },
          {
            "dow": "MON",
            "hh": "08",
            "mm": "10",
            "congestionCar": [
              27,
              38,
              38,
              43,
              40,
              40,
              38,
              46,
              32,
              28
            ]
          },
          {
            "dow": "MON",
            "hh": "08",
            "mm": "20",
            "congestionCar": [
              31,
              36,
              46,
              46,
              49,
              46,
              43,
              48,
              51,
              35
            ]
          },
          {
            "dow": "MON",
            "hh": "08",
            "mm": "30",
            "congestionCar": [
              33,
              32,
              42,
              45,
              54,
              50,
              39,
              58,
              43,
              33
            ]
          },
          {
            "dow": "MON",
            "hh": "08",
            "mm": "40",
            "congestionCar": [
              32,
              34,
              52,
              54,
              48,
              51,
              47,
              51,
              39,
              32
            ]
          },
          {
            "dow": "MON",
            "hh": "08",
            "mm": "50",
            "congestionCar": [
              27,
              34,
              38,
              40,
              33,
              41,
              38,
              40,
              38,
              22
            ]
          }
        ]
      },
      {
        "startStationCode": "211",
        "startStationName": "성수역",
        "endStationCode": "211",
        "endStationName": "성수역",
        "prevStationCode": "242",
        "prevStationName": "아현역",
        "updnLine": 1,
        "directAt": 0,
        "data": [
          {
            "dow": "MON",
            "hh": "08",
            "mm": "00",
            "congestionCar": [
              128,
              107,
              103,
              119,
              108,
              97,
              100,
              91,
              79,
              88
            ]
          },
          {
            "dow": "MON",
            "hh": "08",
            "mm": "10",
            "congestionCar": [
              166,
              141,
              147,
              167,
              158,
              140,
              135,
              137,
              122,
              117
            ]
          },
          {
            "dow": "MON",
            "hh": "08",
            "mm": "20",
            "congestionCar": [
              159,
              140,
              153,
              168,
              148,
              146,
              133,
              152,
              128,
              144
            ]
          },
          {
            "dow": "MON",
            "hh": "08",
            "mm": "30",
            "congestionCar": [
              174,
              159,
              162,
              194,
              175,
              177,
              181,
              173,
              149,
              136
            ]
          },
          {
            "dow": "MON",
            "hh": "08",
            "mm": "40",
            "congestionCar": [
              185,
              150,
              131,
              146,
              127,
              135,
              139,
              125,
              106,
              107
            ]
          },
          {
            "dow": "MON",
            "hh": "08",
            "mm": "50",
            "congestionCar": [
              56,
              40,
              33,
              35,
              37,
              35,
              31,
              32,
              33,
              28
            ]
          }
        ]
      },
      {
        "startStationCode": "211",
        "startStationName": "성수역",
        "endStationCode": "211-R",
        "endStationName": "성수역",
        "prevStationCode": "201",
        "prevStationName": "시청역",
        "updnLine": 0,
        "directAt": 0,
        "data": [
          {
            "dow": "MON",
            "hh": "08",
            "mm": "00",
            "congestionCar": [
              27,
              39,
              42,
              48,
              46,
              41,
              33,
              42,
              35,
              25
            ]
          },
          {
            "dow": "MON",
            "hh": "08",
            "mm": "10",
            "congestionCar": [
              32,
              44,
              45,
              50,
              47,
              47,
              44,
              53,
              37,
              32
            ]
          },
          {
            "dow": "MON",
            "hh": "08",
            "mm": "20",
            "congestionCar": [
              32,
              38,
              48,
              48,
              51,
              48,
              45,
              51,
              53,
              36
            ]
          },
          {
            "dow": "MON",
            "hh": "08",
            "mm": "30",
            "congestionCar": [
              27,
              27,
              36,
              38,
              45,
              41,
              33,
              48,
              36,
              28
            ]
          },
          {
            "dow": "MON",
            "hh": "08",
            "mm": "40",
            "congestionCar": [
              26,
              28,
              42,
              45,
              40,
              42,
              38,
              42,
              32,
              26
            ]
          },
          {
            "dow": "MON",
            "hh": "08",
            "mm": "50",
            "congestionCar": [
              24,
              30,
              34,
              35,
              29,
              36,
              34,
              35,
              33,
              19
            ]
          }
        ]
      },
      {
        "startStationCode": "211",
        "startStationName": "성수역",
        "endStationCode": "211-R",
        "endStationName": "성수역",
        "prevStationCode": "242",
        "prevStationName": "아현역",
        "updnLine": 1,
        "directAt": 0,
        "data": [
          {
            "dow": "MON",
            "hh": "08",
            "mm": "00",
            "congestionCar": [
              137,
              114,
              110,
              127,
              115,
              103,
              107,
              97,
              85,
              94
            ]
          },
          {
            "dow": "MON",
            "hh": "08",
            "mm": "10",
            "congestionCar": [
              166,
              141,
              147,
              167,
              158,
              140,
              135,
              137,
              122,
              117
            ]
          },
          {
            "dow": "MON",
            "hh": "08",
            "mm": "20",
            "congestionCar": [
              159,
              140,
              153,
              168,
              148,
              146,
              133,
              152,
              128,
              144
            ]
          },
          {
            "dow": "MON",
            "hh": "08",
            "mm": "30",
            "congestionCar": [
              174,
              159,
              162,
              194,
              175,
              177,
              181,
              173,
              149,
              136
            ]
          },
          {
            "dow": "MON",
            "hh": "08",
            "mm": "40",
            "congestionCar": [
              191,
              156,
              136,
              151,
              131,
              140,
              144,
              130,
              110,
              111
            ]
          },
          {
            "dow": "MON",
            "hh": "08",
            "mm": "50",
            "congestionCar": [
              120,
              85,
              70,
              75,
              79,
              74,
              66,
              68,
              72,
              61
            ]
          }
        ]
      },
      {
        "startStationCode": "211",
        "startStationName": "성수역",
        "endStationCode": "219",
        "endStationName": "삼성역",
        "prevStationCode": "201",
        "prevStationName": "시청역",
        "updnLine": 0,
        "directAt": 0,
        "data": [
          {
            "dow": "MON",
            "hh": "08",
            "mm": "00",
            "congestionCar": [
              27,
              38,
              41,
              47,
              45,
              40,
              32,
              41,
              34,
              25
            ]
          },
          {
            "dow": "MON",
            "hh": "08",
            "mm": "10",
            "congestionCar": [
              31,
              43,
              44,
              49,
              46,
              46,
              43,
              52,
              36,
              32
            ]
          },
          {
            "dow": "MON",
            "hh": "08",
            "mm": "20",
            "congestionCar": [
              31,
              37,
              47,
              47,
              50,
              47,
              44,
              49,
              52,
              35
            ]
          },
          {
            "dow": "MON",
            "hh": "08",
            "mm": "30",
            "congestionCar": [
              29,
              29,
              38,
              40,
              48,
              44,
              35,
              51,
              38,
              29
            ]
          },
          {
            "dow": "MON",
            "hh": "08",
            "mm": "40",
            "congestionCar": [
              27,
              29,
              45,
              47,
              42,
              44,
              41,
              44,
              34,
              27
            ]
          },
          {
            "dow": "MON",
            "hh": "08",
            "mm": "50",
            "congestionCar": [
              25,
              31,
              35,
              36,
              30,
              37,
              35,
              36,
              34,
              20
            ]
          }
        ]
      },
      {
        "startStationCode": "211",
        "startStationName": "성수역",
        "endStationCode": "228",
        "endStationName": "서울대입구역",
        "prevStationCode": "201",
        "prevStationName": "시청역",
        "updnLine": 0,
        "directAt": 0,
        "data": [
          {
            "dow": "MON",
            "hh": "08",
            "mm": "00",
            "congestionCar": [
              27,
              38,
              41,
              47,
              45,
              40,
              32,
              41,
              34,
              25
            ]
          },
          {
            "dow": "MON",
            "hh": "08",
            "mm": "10",
            "congestionCar": [
              31,
              43,
              44,
              49,
              46,
              46,
              43,
              52,
              36,
              32
            ]
          },
          {
            "dow": "MON",
            "hh": "08",
            "mm": "20",
            "congestionCar": [
              31,
              37,
              47,
              47,
              50,
              47,
              44,
              49,
              52,
              35
            ]
          },
          {
            "dow": "MON",
            "hh": "08",
            "mm": "30",
            "congestionCar": [
              29,
              29,
              38,
              40,
              48,
              44,
              35,
              51,
              38,
              29
            ]
          },
          {
            "dow": "MON",
            "hh": "08",
            "mm": "40",
            "congestionCar": [
              27,
              29,
              45,
              47,
              42,
              44,
              41,
              44,
              34,
              27
            ]
          },
          {
            "dow": "MON",
            "hh": "08",
            "mm": "50",
            "congestionCar": [
              25,
              31,
              35,
              36,
              30,
              37,
              35,
              36,
              34,
              20
            ]
          }
        ]
      },
      {
        "startStationCode": "211",
        "startStationName": "성수역",
        "endStationCode": "234",
        "endStationName": "신도림역",
        "prevStationCode": "201",
        "prevStationName": "시청역",
        "updnLine": 0,
        "directAt": 0,
        "data": [
          {
            "dow": "MON",
            "hh": "08",
            "mm": "00",
            "congestionCar": [
              27,
              38,
              41,
              47,
              45,
              40,
              32,
              41,
              34,
              25
            ]
          },
          {
            "dow": "MON",
            "hh": "08",
            "mm": "10",
            "congestionCar": [
              31,
              43,
              44,
              49,
              46,
              46,
              43,
              52,
              36,
              32
            ]
          },
          {
            "dow": "MON",
            "hh": "08",
            "mm": "20",
            "congestionCar": [
              14,
              17,
              21,
              21,
              23,
              21,
              20,
              22,
              24,
              16
            ]
          },
          {
            "dow": "MON",
            "hh": "08",
            "mm": "30",
            "congestionCar": [
              31,
              31,
              40,
              43,
              52,
              47,
              38,
              55,
              41,
              32
            ]
          },
          {
            "dow": "MON",
            "hh": "08",
            "mm": "40",
            "congestionCar": [
              30,
              32,
              48,
              51,
              45,
              47,
              44,
              47,
              36,
              30
            ]
          },
          {
            "dow": "MON",
            "hh": "08",
            "mm": "50",
            "congestionCar": [
              24,
              30,
              34,
              35,
              29,
              36,
              34,
              35,
              33,
              19
            ]
          }
        ]
      },
      {
        "startStationCode": "211",
        "startStationName": "성수역",
        "endStationCode": "239",
        "endStationName": "홍대입구역",
        "prevStationCode": "201",
        "prevStationName": "시청역",
        "updnLine": 0,
        "directAt": 0,
        "data": [
          {
            "dow": "MON",
            "hh": "08",
            "mm": "00",
            "congestionCar": [
              27,
              38,
              41,
              47,
              45,
              40,
              32,
              41,
              34,
              25
            ]
          },
          {
            "dow": "MON",
            "hh": "08",
            "mm": "10",
            "congestionCar": [
              31,
              43,
              44,
              49,
              46,
              46,
              43,
              52,
              36,
              32
            ]
          },
          {
            "dow": "MON",
            "hh": "08",
            "mm": "20",
            "congestionCar": [
              31,
              37,
              47,
              47,
              50,
              47,
              44,
              49,
              52,
              35
            ]
          },
          {
            "dow": "MON",
            "hh": "08",
            "mm": "30",
            "congestionCar": [
              29,
              29,
              38,
              40,
              48,
              44,
              35,
              51,
              38,
              29
            ]
          },
          {
            "dow": "MON",
            "hh": "08",
            "mm": "40",
            "congestionCar": [
              27,
              29,
              45,
              47,
              42,
              44,
              41,
              44,
              34,
              27
            ]
          },
          {
            "dow": "MON",
            "hh": "08",
            "mm": "50",
            "congestionCar": [
              25,
              31,
              35,
              36,
              30,
              37,
              35,
              36,
              34,
              20
            ]
          }
        ]
      },
      {
        "startStationCode": "219",
        "startStationName": "삼성역",
        "endStationCode": "211-R",
        "endStationName": "성수역",
        "prevStationCode": "242",
        "prevStationName": "아현역",
        "updnLine": 1,
        "directAt": 0,
        "data": [
          {
            "dow": "MON",
            "hh": "08",
            "mm": "00",
            "congestionCar": [
              128,
              107,
              103,
              119,
              108,
              97,
              100,
              91,
              79,
              88
            ]
          },
          {
            "dow": "MON",
            "hh": "08",
            "mm": "10",
            "congestionCar": [
              166,
              141,
              147,
              167,
              158,
              140,
              135,
              137,
              122,
              117
            ]
          },
          {
            "dow": "MON",
            "hh": "08",
            "mm": "20",
            "congestionCar": [
              159,
              140,
              153,
              168,
              148,
              146,
              133,
              152,
              128,
              144
            ]
          },
          {
            "dow": "MON",
            "hh": "08",
            "mm": "30",
            "congestionCar": [
              174,
              159,
              162,
              194,
              175,
              177,
              181,
              173,
              149,
              136
            ]
          },
          {
            "dow": "MON",
            "hh": "08",
            "mm": "40",
            "congestionCar": [
              185,
              150,
              131,
              146,
              127,
              135,
              139,
              125,
              106,
              107
            ]
          },
          {
            "dow": "MON",
            "hh": "08",
            "mm": "50",
            "congestionCar": [
              117,
              83,
              69,
              73,
              77,
              72,
              64,
              66,
              70,
              59
            ]
          }
        ]
      },
      {
        "startStationCode": "228",
        "startStationName": "서울대입구역",
        "endStationCode": "211",
        "endStationName": "성수역",
        "prevStationCode": "242",
        "prevStationName": "아현역",
        "updnLine": 1,
        "directAt": 0,
        "data": [
          {
            "dow": "MON",
            "hh": "08",
            "mm": "00",
            "congestionCar": [
              128,
              107,
              103,
              119,
              108,
              97,
              100,
              91,
              79,
              88
            ]
          },
          {
            "dow": "MON",
            "hh": "08",
            "mm": "10",
            "congestionCar": [
              166,
              141,
              147,
              167,
              158,
              140,
              135,
              137,
              122,
              117
            ]
          },
          {
            "dow": "MON",
            "hh": "08",
            "mm": "20",
            "congestionCar": [
              159,
              140,
              153,
              168,
              148,
              146,
              133,
              152,
              128,
              144
            ]
          },
          {
            "dow": "MON",
            "hh": "08",
            "mm": "30",
            "congestionCar": [
              174,
              159,
              162,
              194,
              175,
              177,
              181,
              173,
              149,
              136
            ]
          },
          {
            "dow": "MON",
            "hh": "08",
            "mm": "40",
            "congestionCar": [
              185,
              150,
              131,
              146,
              127,
              135,
              139,
              125,
              106,
              107
            ]
          },
          {
            "dow": "MON",
            "hh": "08",
            "mm": "50",
            "congestionCar": [
              117,
              83,
              69,
              73,
              77,
              72,
              64,
              66,
              70,
              59
            ]
          }
        ]
      },
      {
        "startStationCode": "228",
        "startStationName": "서울대입구역",
        "endStationCode": "211-R",
        "endStationName": "성수역",
        "prevStationCode": "242",
        "prevStationName": "아현역",
        "updnLine": 1,
        "directAt": 0,
        "data": [
          {
            "dow": "MON",
            "hh": "08",
            "mm": "00",
            "congestionCar": [
              128,
              107,
              103,
              119,
              108,
              97,
              100,
              91,
              79,
              88
            ]
          },
          {
            "dow": "MON",
            "hh": "08",
            "mm": "10",
            "congestionCar": [
              166,
              141,
              147,
              167,
              158,
              140,
              135,
              137,
              122,
              117
            ]
          },
          {
            "dow": "MON",
            "hh": "08",
            "mm": "20",
            "congestionCar": [
              159,
              140,
              153,
              168,
              148,
              146,
              133,
              152,
              128,
              144
            ]
          },
          {
            "dow": "MON",
            "hh": "08",
            "mm": "30",
            "congestionCar": [
              174,
              159,
              162,
              194,
              175,
              177,
              181,
              173,
              149,
              136
            ]
          },
          {
            "dow": "MON",
            "hh": "08",
            "mm": "40",
            "congestionCar": [
              185,
              150,
              131,
              146,
              127,
              135,
              139,
              125,
              106,
              107
            ]
          },
          {
            "dow": "MON",
            "hh": "08",
            "mm": "50",
            "congestionCar": [
              117,
              83,
              69,
              73,
              77,
              72,
              64,
              66,
              70,
              59
            ]
          }
        ]
      },
      {
        "startStationCode": "234",
        "startStationName": "신도림역",
        "endStationCode": "211",
        "endStationName": "성수역",
        "prevStationCode": "242",
        "prevStationName": "아현역",
        "updnLine": 1,
        "directAt": 0,
        "data": [
          {
            "dow": "MON",
            "hh": "08",
            "mm": "00",
            "congestionCar": [
              128,
              107,
              103,
              119,
              108,
              97,
              100,
              91,
              79,
              88
            ]
          },
          {
            "dow": "MON",
            "hh": "08",
            "mm": "10",
            "congestionCar": [
              166,
              141,
              147,
              167,
              158,
              140,
              135,
              137,
              122,
              117
            ]
          },
          {
            "dow": "MON",
            "hh": "08",
            "mm": "20",
            "congestionCar": [
              159,
              140,
              153,
              168,
              148,
              146,
              133,
              152,
              128,
              144
            ]
          },
          {
            "dow": "MON",
            "hh": "08",
            "mm": "30",
            "congestionCar": [
              174,
              159,
              162,
              194,
              175,
              177,
              181,
              173,
              149,
              136
            ]
          },
          {
            "dow": "MON",
            "hh": "08",
            "mm": "40",
            "congestionCar": [
              185,
              150,
              131,
              146,
              127,
              135,
              139,
              125,
              106,
              107
            ]
          },
          {
            "dow": "MON",
            "hh": "08",
            "mm": "50",
            "congestionCar": [
              117,
              83,
              69,
              73,
              77,
              72,
              64,
              66,
              70,
              59
            ]
          }
        ]
      },
      {
        "startStationCode": "234",
        "startStationName": "신도림역",
        "endStationCode": "211-R",
        "endStationName": "성수역",
        "prevStationCode": "242",
        "prevStationName": "아현역",
        "updnLine": 1,
        "directAt": 0,
        "data": [
          {
            "dow": "MON",
            "hh": "08",
            "mm": "00",
            "congestionCar": [
              107,
              89,
              86,
              99,
              90,
              81,
              84,
              76,
              66,
              73
            ]
          },
          {
            "dow": "MON",
            "hh": "08",
            "mm": "10",
            "congestionCar": [
              50,
              42,
              44,
              50,
              47,
              42,
              41,
              41,
              37,
              35
            ]
          },
          {
            "dow": "MON",
            "hh": "08",
            "mm": "20",
            "congestionCar": [
              159,
              140,
              153,
              168,
              148,
              146,
              133,
              152,
              128,
              144
            ]
          },
          {
            "dow": "MON",
            "hh": "08",
            "mm": "30",
            "congestionCar": [
              174,
              159,
              162,
              194,
              175,
              177,
              181,
              173,
              149,
              136
            ]
          },
          {
            "dow": "MON",
            "hh": "08",
            "mm": "40",
            "congestionCar": [
              185,
              150,
              131,
              146,
              127,
              135,
              139,
              125,
              106,
              107
            ]
          },
          {
            "dow": "MON",
            "hh": "08",
            "mm": "50",
            "congestionCar": [
              117,
              83,
              69,
              73,
              77,
              72,
              64,
              66,
              70,
              59
            ]
          }
        ]
      },
      {
        "startStationCode": "239",
        "startStationName": "홍대입구역",
        "endStationCode": "211",
        "endStationName": "성수역",
        "prevStationCode": "242",
        "prevStationName": "아현역",
        "updnLine": 1,
        "directAt": 0,
        "data": [
          {
            "dow": "MON",
            "hh": "08",
            "mm": "00",
            "congestionCar": [
              128,
              107,
              103,
              119,
              108,
              97,
              100,
              91,
              79,
              88
            ]
          },
          {
            "dow": "MON",
            "hh": "08",
            "mm": "10",
            "congestionCar": [
              166,
              141,
              147,
              167,
              158,
              140,
              135,
              137,
              122,
              117
            ]
          },
          {
            "dow": "MON",
            "hh": "08",
            "mm": "20",
            "congestionCar": [
              159,
              140,
              153,
              168,
              148,
              146,
              133,
              152,
              128,
              144
            ]
          },
          {
            "dow": "MON",
            "hh": "08",
            "mm": "30",
            "congestionCar": [
              174,
              159,
              162,
              194,
              175,
              177,
              181,
              173,
              149,
              136
            ]
          },
          {
            "dow": "MON",
            "hh": "08",
            "mm": "40",
            "congestionCar": [
              185,
              150,
              131,
              146,
              127,
              135,
              139,
              125,
              106,
              107
            ]
          },
          {
            "dow": "MON",
            "hh": "08",
            "mm": "50",
            "congestionCar": [
              117,
              83,
              69,
              73,
              77,
              72,
              64,
              66,
              70,
              59
            ]
          }
        ]
      },
      {
        "startStationCode": "239",
        "startStationName": "홍대입구역",
        "endStationCode": "211-R",
        "endStationName": "성수역",
        "prevStationCode": "242",
        "prevStationName": "아현역",
        "updnLine": 1,
        "directAt": 0,
        "data": [
          {
            "dow": "MON",
            "hh": "08",
            "mm": "00",
            "congestionCar": [
              128,
              107,
              103,
              119,
              108,
              97,
              100,
              91,
              79,
              88
            ]
          },
          {
            "dow": "MON",
            "hh": "08",
            "mm": "10",
            "congestionCar": [
              166,
              141,
              147,
              167,
              158,
              140,
              135,
              137,
              122,
              117
            ]
          },
          {
            "dow": "MON",
            "hh": "08",
            "mm": "20",
            "congestionCar": [
              159,
              140,
              153,
              168,
              148,
              146,
              133,
              152,
              128,
              144
            ]
          },
          {
            "dow": "MON",
            "hh": "08",
            "mm": "30",
            "congestionCar": [
              174,
              159,
              162,
              194,
              175,
              177,
              181,
              173,
              149,
              136
            ]
          },
          {
            "dow": "MON",
            "hh": "08",
            "mm": "40",
            "congestionCar": [
              185,
              150,
              131,
              146,
              127,
              135,
              139,
              125,
              106,
              107
            ]
          },
          {
            "dow": "MON",
            "hh": "08",
            "mm": "50",
            "congestionCar": [
              117,
              83,
              69,
              73,
              77,
              72,
              64,
              66,
              70,
              59
            ]
          }
        ]
      }
    ],
    "statStartDate": "20230924",
    "statEndDate": "20231223"
  }
}